[{"Title":"Zeridium & Render – Riot In A Teacup","Title_URL":"https://soundcloud.com/zeridium/zeridium-render-riot-in-a-teacup-out-on-sahman-records-on-the-0304","User":"\n                ZERIDIUM\n            ","User1":"","Time":"Posted 1 year ago\n1 year ago","Tag_URL":"https://soundcloud.com/tags/street%20psytrance","Content":"Street Psytrance","Like":"345","scbuttonrepost":"35","scbuttoncopylink":"Copy Link","soundactions_purchaselink_URL":"","soundactions_purchaselink":"","scbuttonmore":"More","scministats":"6,784","Comment_URL":"https://soundcloud.com/zeridium/zeridium-render-riot-in-a-teacup-out-on-sahman-records-on-the-0304/comments","Comment":"16"},{"Title":"Zeridium - Possession EP (Minimix) Out on the 09/12 on Future Music Records","Title_URL":"https://soundcloud.com/zeridium/zeridium-possession-ep-minimix-out-on-the-0912-on-future-music-records","User":"\n                ZERIDIUM\n            ","User1":"","Time":"Posted 1 month ago\n1 month ago","Tag_URL":"https://soundcloud.com/tags/psytrance","Content":"Psytrance","Like":"76","scbuttonrepost":"22","scbuttoncopylink":"Copy Link","soundactions_purchaselink_URL":"","soundactions_purchaselink":"","scbuttonmore":"More","scministats":"1,131","Comment_URL":"https://soundcloud.com/zeridium/zeridium-possession-ep-minimix-out-on-the-0912-on-future-music-records/comments","Comment":"22"},{"Title":"Zeridium & Rugrats - Radio One Zero Sick (Out on now Looney Moon Records)","Title_URL":"https://soundcloud.com/zeridium/zeridium-rugrats-radio-one-zero-sickk","User":"\n                ZERIDIUM\n            ","User1":"","Time":"Posted 7 months ago\n7 months ago","Tag_URL":"https://soundcloud.com/tags/urban-psy","Content":"Urban-Psy","Like":"469","scbuttonrepost":"50","scbuttoncopylink":"Copy Link","soundactions_purchaselink_URL":"","soundactions_purchaselink":"","scbuttonmore":"More","scministats":"7,444","Comment_URL":"https://soundcloud.com/zeridium/zeridium-rugrats-radio-one-zero-sickk/comments","Comment":"43"},{"Title":"Zeridium vs LabRat @ Shiva Valley, Goa","Title_URL":"https://soundcloud.com/zeridium/zeridium-vs-labrat-shiva-valley-goa","User":"\n                ZERIDIUM\n            ","User1":"","Time":"Posted 11 months ago\n11 months ago","Tag_URL":"https://soundcloud.com/tags/psytrance","Content":"Psytrance","Like":"961","scbuttonrepost":"85","scbuttoncopylink":"Copy Link","soundactions_purchaselink_URL":"","soundactions_purchaselink":"","scbuttonmore":"More","scministats":"16K","Comment_URL":"https://soundcloud.com/zeridium/zeridium-vs-labrat-shiva-valley-goa/comments","Comment":"67"},{"Title":"Zeridium & Inside Mind - Kerozen","Title_URL":"https://soundcloud.com/zeridium/zeridium-inside-mind-kerozen-out-on-sahman-records-on-the-0311","User":"\n                ZERIDIUM\n            ","User1":"","Time":"Posted 1 year ago\n1 year ago","Tag_URL":"https://soundcloud.com/tags/psytrance","Content":"Psytrance","Like":"551","scbuttonrepost":"61","scbuttoncopylink":"Copy Link","soundactions_purchaselink_URL":"","soundactions_purchaselink":"","scbuttonmore":"More","scministats":"12.3K","Comment_URL":"https://soundcloud.com/zeridium/zeridium-inside-mind-kerozen-out-on-sahman-records-on-the-0311/comments","Comment":"39"},{"Title":"Minimix Zeridium \"The 13 best tracks released on Sahman Records\"","Title_URL":"https://soundcloud.com/zeridium/minimix-zeridium-the-14-best-tracks-released-on-sahman-records","User":"\n                ZERIDIUM\n            ","User1":"","Time":"Posted 10 days ago\n10 days ago","Tag_URL":"https://soundcloud.com/tags/psytrance","Content":"psytrance","Like":"79","scbuttonrepost":"17","scbuttoncopylink":"Copy Link","soundactions_purchaselink_URL":"","soundactions_purchaselink":"","scbuttonmore":"More","scministats":"654","Comment_URL":"https://soundcloud.com/zeridium/minimix-zeridium-the-14-best-tracks-released-on-sahman-records/comments","Comment":"6"},{"Title":"Possession (Original mix)","Title_URL":"https://soundcloud.com/zeridium/possession-original-mix","User":"\n                Zeridium\n            ","User1":"","Time":"Posted 1 month ago\n1 month ago","Tag_URL":"https://soundcloud.com/tags/electronic","Content":"Electronic","Like":"30","scbuttonrepost":"8","scbuttoncopylink":"Copy Link","soundactions_purchaselink_URL":"","soundactions_purchaselink":"","scbuttonmore":"More","scministats":"348","Comment_URL":"https://soundcloud.com/zeridium/possession-original-mix/comments","Comment":"5"},{"Title":"Betrayal (Original mix)","Title_URL":"https://soundcloud.com/zeridium/betrayal-original-mix","User":"\n                Zeridium\n            ","User1":"","Time":"Posted 1 month ago\n1 month ago","Tag_URL":"https://soundcloud.com/tags/electronic","Content":"Electronic","Like":"23","scbuttonrepost":"4","scbuttoncopylink":"Copy Link","soundactions_purchaselink_URL":"","soundactions_purchaselink":"","scbuttonmore":"More","scministats":"284","Comment_URL":"https://soundcloud.com/zeridium/betrayal-original-mix/comments","Comment":"3"},{"Title":"Possession","Title_URL":"https://soundcloud.com/zeridium/sets/possession-916365977","User":"\n                ZERIDIUM\n            ","User1":"","Time":"Posted 1 month ago\n1 month ago","Tag_URL":"https://soundcloud.com/tags/electronic","Content":"Electronic","Like":"8","scbuttonrepost":"1","scbuttoncopylink":"Copy Link","soundactions_purchaselink_URL":"","soundactions_purchaselink":"","scbuttonmore":"","scministats":"","Comment_URL":"","Comment":""},{"Title":"B2B set Johnny Void & Akhos @ People are Strange 2024","Title_URL":"https://soundcloud.com/johnny-void/b2b-set-johnny-void-akhos-people-are-strange-2024","User":"\n                Johnny Void & Akhos\n            ","User1":"\n  ZERIDIUM\n","Time":"Reposted 1 month ago\n1 month ago","Tag_URL":"https://soundcloud.com/tags/techno%20psy-indus","Content":"Techno Psy-indus","Like":"9","scbuttonrepost":"2","scbuttoncopylink":"Copy Link","soundactions_purchaselink_URL":"","soundactions_purchaselink":"","scbuttonmore":"More","scministats":"186","Comment_URL":"https://soundcloud.com/johnny-void/b2b-set-johnny-void-akhos-people-are-strange-2024/comments","Comment":"1"},{"Title":"Urban Psytrance vol.1 (Compiled by Kneeko)","Title_URL":"https://soundcloud.com/blastpolis/sets/urbanpsyvol1","User":"\n                Blastpolis Music\n            ","User1":"\n  ZERIDIUM\n","Time":"Reposted 2 months ago\n2 months ago","Tag_URL":"https://soundcloud.com/tags/urban%20psytrance","Content":"Urban Psytrance","Like":"72","scbuttonrepost":"20","scbuttoncopylink":"Copy Link","soundactions_purchaselink_URL":"","soundactions_purchaselink":"","scbuttonmore":"","scministats":"","Comment_URL":"","Comment":""},{"Title":"Zeridium - Louder Than Chuck Norizz","Title_URL":"https://soundcloud.com/blastpolis/zeridium-louder-than-chuck","User":"\n                Blastpolis Music\n            ","User1":"\n  ZERIDIUM\n","Time":"Reposted 2 months ago\n2 months ago","Tag_URL":"","Content":"","Like":"49","scbuttonrepost":"7","scbuttoncopylink":"Copy Link","soundactions_purchaselink_URL":"","soundactions_purchaselink":"","scbuttonmore":"More","scministats":"1,167","Comment_URL":"https://soundcloud.com/blastpolis/zeridium-louder-than-chuck/comments","Comment":"2"},{"Title":"Johnny Void & Akhos - Katacomb (preview) Out on Zenon Records","Title_URL":"https://soundcloud.com/johnny-void/johnny-void-akhos-katacomb-out-on-zenon-records-on-the-1804","User":"\n                JOHNNY VOID\n            ","User1":"\n  ZERIDIUM\n","Time":"Reposted 9 months ago\n9 months ago","Tag_URL":"https://soundcloud.com/tags/techno","Content":"Techno","Like":"187","scbuttonrepost":"7","scbuttoncopylink":"Copy Link","soundactions_purchaselink_URL":"","soundactions_purchaselink":"","scbuttonmore":"More","scministats":"10.2K","Comment_URL":"https://soundcloud.com/johnny-void/johnny-void-akhos-katacomb-out-on-zenon-records-on-the-1804/comments","Comment":"9"},{"Title":"ZERIDIUM | Sahman Records Series Ep. 15 | 02/02/2024","Title_URL":"https://soundcloud.com/radiozora/zeridium-sahman-series-15","User":"\n                radiOzora\n            ","User1":"\n  ZERIDIUM\n","Time":"Reposted 10 months ago\n10 months ago","Tag_URL":"https://soundcloud.com/tags/psy%20trance","Content":"psy trance","Like":"445","scbuttonrepost":"53","scbuttoncopylink":"Copy Link","soundactions_purchaselink_URL":"https://soundcloud.com/radiozora/sets/sahman-records-series","soundactions_purchaselink":"Atchives","scbuttonmore":"More","scministats":"7,830","Comment_URL":"https://soundcloud.com/radiozora/zeridium-sahman-series-15/comments","Comment":"16"},{"Title":"Zeridium & Virtual Light - Shikaka (Out on Grasshopper Records)","Title_URL":"https://soundcloud.com/zeridium/zeridium-virtual-light-shikaka-out-today-on-grasshopper-records","User":"\n                ZERIDIUM\n            ","User1":"","Time":"Posted 1 year ago\n1 year ago","Tag_URL":"https://soundcloud.com/tags/psytrance","Content":"Psytrance","Like":"360","scbuttonrepost":"44","scbuttoncopylink":"Copy Link","soundactions_purchaselink_URL":"","soundactions_purchaselink":"","scbuttonmore":"More","scministats":"6,426","Comment_URL":"https://soundcloud.com/zeridium/zeridium-virtual-light-shikaka-out-today-on-grasshopper-records/comments","Comment":"16"},{"Title":"Zeridium & Jungli - Aroha","Title_URL":"https://soundcloud.com/zeridium/zeridium-jungli-ahora-out-on-the-1809-on-sahman-records","User":"\n                ZERIDIUM\n            ","User1":"","Time":"Posted 1 year ago\n1 year ago","Tag_URL":"https://soundcloud.com/tags/psytrance","Content":"Psytrance","Like":"355","scbuttonrepost":"44","scbuttoncopylink":"Copy Link","soundactions_purchaselink_URL":"","soundactions_purchaselink":"","scbuttonmore":"More","scministats":"6,407","Comment_URL":"https://soundcloud.com/zeridium/zeridium-jungli-ahora-out-on-the-1809-on-sahman-records/comments","Comment":"27"},{"Title":"Zeridium & Slip Hypnotic - Salade de Thon - Out on Zenon Records","Title_URL":"https://soundcloud.com/zeridium/zeridium-slip-hypnotic-salade-de-thon-out-on-zenon-records-on-the-1805","User":"\n                ZERIDIUM\n            ","User1":"","Time":"Posted 1 year ago\n1 year ago","Tag_URL":"https://soundcloud.com/tags/fullon%20darkprog","Content":"Fullon Darkprog","Like":"199","scbuttonrepost":"32","scbuttoncopylink":"Copy Link","soundactions_purchaselink_URL":"","soundactions_purchaselink":"","scbuttonmore":"More","scministats":"4,125","Comment_URL":"https://soundcloud.com/zeridium/zeridium-slip-hypnotic-salade-de-thon-out-on-zenon-records-on-the-1805/comments","Comment":"15"},{"Title":"Zeridium - Acid Rumble - Out on Protoned Records","Title_URL":"https://soundcloud.com/zeridium/zeridium-acid-rumble-out-today-on-protoned-records","User":"\n                ZERIDIUM\n            ","User1":"","Time":"Posted 1 year ago\n1 year ago","Tag_URL":"https://soundcloud.com/tags/psy-acid","Content":"Psy-Acid","Like":"532","scbuttonrepost":"67","scbuttoncopylink":"Copy Link","soundactions_purchaselink_URL":"","soundactions_purchaselink":"","scbuttonmore":"More","scministats":"8,809","Comment_URL":"https://soundcloud.com/zeridium/zeridium-acid-rumble-out-today-on-protoned-records/comments","Comment":"23"},{"Title":"Zeridium vs Duke&Gonzo - Three Funky Fokers","Title_URL":"https://soundcloud.com/zeridium/3-funky-fokers-preview","User":"\n                ZERIDIUM\n            ","User1":"","Time":"Posted 1 year ago\n1 year ago","Tag_URL":"https://soundcloud.com/tags/psytrance","Content":"Psytrance","Like":"405","scbuttonrepost":"47","scbuttoncopylink":"Copy Link","soundactions_purchaselink_URL":"","soundactions_purchaselink":"","scbuttonmore":"More","scministats":"7,212","Comment_URL":"https://soundcloud.com/zeridium/3-funky-fokers-preview/comments","Comment":"24"},{"Title":"ZERIDIUM | Sahman Records Series Ep. 7 | 01/11/2022","Title_URL":"https://soundcloud.com/radiozora/zeridium-sahman-records-series-ep-7-01112022","User":"\n                radiOzora\n            ","User1":"\n  ZERIDIUM\n","Time":"Reposted 2 years ago\n2 years ago","Tag_URL":"https://soundcloud.com/tags/fullon%20/%20twilight","Content":"fullon / twilight","Like":"462","scbuttonrepost":"78","scbuttoncopylink":"Copy Link","soundactions_purchaselink_URL":"https://soundcloud.com/radiozora/sets/sahman-records-series","soundactions_purchaselink":"More episodes","scbuttonmore":"More","scministats":"6,824","Comment_URL":"https://soundcloud.com/radiozora/zeridium-sahman-records-series-ep-7-01112022/comments","Comment":"28"},{"Title":"Zeridium & Formantz - Monkey Poetry (out on Blacklite Records!!!)","Title_URL":"https://soundcloud.com/zeridium/zeridium-formantz-monkey-poetry-out-on-blacklite-records-on-the-1111","User":"\n                ZERIDIUM\n            ","User1":"","Time":"Posted 2 years ago\n2 years ago","Tag_URL":"https://soundcloud.com/tags/psytance","Content":"Psytance","Like":"266","scbuttonrepost":"37","scbuttoncopylink":"Copy Link","soundactions_purchaselink_URL":"","soundactions_purchaselink":"","scbuttonmore":"More","scministats":"4,836","Comment_URL":"https://soundcloud.com/zeridium/zeridium-formantz-monkey-poetry-out-on-blacklite-records-on-the-1111/comments","Comment":"11"},{"Title":"Zeridium & Siloka - This One is for Your Mom","Title_URL":"https://soundcloud.com/zeridium/zeridium-siloka-this-one-is-for-your-mom","User":"\n                ZERIDIUM\n            ","User1":"","Time":"Posted 2 years ago\n2 years ago","Tag_URL":"https://soundcloud.com/tags/neuro%20psytrance","Content":"Neuro Psytrance","Like":"615","scbuttonrepost":"75","scbuttoncopylink":"Copy Link","soundactions_purchaselink_URL":"","soundactions_purchaselink":"","scbuttonmore":"More","scministats":"12K","Comment_URL":"https://soundcloud.com/zeridium/zeridium-siloka-this-one-is-for-your-mom/comments","Comment":"37"},{"Title":"Zeridium - Ghetto Blaster || OUT NOW @ Sahman Records","Title_URL":"https://soundcloud.com/zeridium/zeridium-ghetto-blaster-out-next-week-sahman-records","User":"\n                ZERIDIUM\n            ","User1":"","Time":"Posted 2 years ago\n2 years ago","Tag_URL":"https://soundcloud.com/tags/psytrance","Content":"Psytrance","Like":"318","scbuttonrepost":"47","scbuttoncopylink":"Copy Link","soundactions_purchaselink_URL":"https://gate.sc/?url=https%3A%2F%2Fbit.ly%2F3FiWlXu&token=d0b5da-1-1736523129173","soundactions_purchaselink":"Pre-order","scbuttonmore":"More","scministats":"5,497","Comment_URL":"https://soundcloud.com/zeridium/zeridium-ghetto-blaster-out-next-week-sahman-records/comments","Comment":"40"},{"Title":"Zeridium Classic Tracks, Vol.1","Title_URL":"https://soundcloud.com/zeridium/sets/zeridium-classic-tracks-vol-1","User":"\n                ZERIDIUM\n            ","User1":"","Time":"Posted 2 years ago\n2 years ago","Tag_URL":"https://soundcloud.com/tags/psytrance","Content":"Psytrance","Like":"83","scbuttonrepost":"28","scbuttoncopylink":"Copy Link","soundactions_purchaselink_URL":"https://gate.sc/?url=https%3A%2F%2Flnkfi.re%2Fzeridiumclasictracks&token=ff2f20-1-1736523129196","soundactions_purchaselink":"All platforms","scbuttonmore":"","scministats":"","Comment_URL":"","Comment":""},{"Title":"Plastic Jungle (Original Mix)","Title_URL":"https://soundcloud.com/zeridium/plastic-jungle-original-mix","User":"\n                Zeridium, Mosba\n            ","User1":"","Time":"Posted 3 years ago\n3 years ago","Tag_URL":"https://soundcloud.com/tags/electronic","Content":"Electronic","Like":"69","scbuttonrepost":"10","scbuttoncopylink":"Copy Link","soundactions_purchaselink_URL":"","soundactions_purchaselink":"","scbuttonmore":"More","scministats":"926","Comment_URL":"https://soundcloud.com/zeridium/plastic-jungle-original-mix/comments","Comment":"4"},{"Title":"Zeridium & Mosba - Plastic Jungle || Out on Blacklite Records","Title_URL":"https://soundcloud.com/zeridium/zeridium-mosba-plastic-jungle-out-on-blacklite-records-on-the-2910-preview","User":"\n                ZERIDIUM\n            ","User1":"","Time":"Posted 3 years ago\n3 years ago","Tag_URL":"https://soundcloud.com/tags/psytrance","Content":"Psytrance","Like":"593","scbuttonrepost":"82","scbuttoncopylink":"Copy Link","soundactions_purchaselink_URL":"","soundactions_purchaselink":"","scbuttonmore":"More","scministats":"10.3K","Comment_URL":"https://soundcloud.com/zeridium/zeridium-mosba-plastic-jungle-out-on-blacklite-records-on-the-2910-preview/comments","Comment":"22"},{"Title":"Zeridium - WoodWoody (Remix 2021) || FREE DOWNLOAD","Title_URL":"https://soundcloud.com/zeridium/zeridium-woodwoody-remix-2021-free-download","User":"\n                ZERIDIUM\n            ","User1":"","Time":"Posted 3 years ago\n3 years ago","Tag_URL":"https://soundcloud.com/tags/psytrance","Content":"Psytrance","Like":"1,065","scbuttonrepost":"318","scbuttoncopylink":"Copy Link","soundactions_purchaselink_URL":"https://gate.sc/?url=https%3A%2F%2Fhypeddit.com%2Ftrack%2Fff90dw&token=6d7c24-1-1736523135119","soundactions_purchaselink":"Free Download","scbuttonmore":"More","scministats":"16.2K","Comment_URL":"https://soundcloud.com/zeridium/zeridium-woodwoody-remix-2021-free-download/comments","Comment":"36"},{"Title":"Zeridium - Röntgen Void","Title_URL":"https://soundcloud.com/zeridium/zeridium-rontgen-void-preview-out-2607-sahman-records","User":"\n                ZERIDIUM\n            ","User1":"","Time":"Posted 3 years ago\n3 years ago","Tag_URL":"https://soundcloud.com/tags/psytrance","Content":"psytrance","Like":"407","scbuttonrepost":"62","scbuttoncopylink":"Copy Link","soundactions_purchaselink_URL":"https://gate.sc/?url=https%3A%2F%2Fbit.ly%2F3ioGITa&token=6fc4d3-1-1736523135139","soundactions_purchaselink":"PRE-ORDER","scbuttonmore":"More","scministats":"7,329","Comment_URL":"https://soundcloud.com/zeridium/zeridium-rontgen-void-preview-out-2607-sahman-records/comments","Comment":"39"},{"Title":"Zeridium Live-set @ Château Perché Festival","Title_URL":"https://soundcloud.com/zeridium/zeridium-summer-live-set-2021","User":"\n                ZERIDIUM\n            ","User1":"","Time":"Posted 3 years ago\n3 years ago","Tag_URL":"https://soundcloud.com/tags/psytrance","Content":"Psytrance","Like":"1,098","scbuttonrepost":"141","scbuttoncopylink":"Copy Link","soundactions_purchaselink_URL":"","soundactions_purchaselink":"","scbuttonmore":"More","scministats":"17.9K","Comment_URL":"https://soundcloud.com/zeridium/zeridium-summer-live-set-2021/comments","Comment":"63"},{"Title":"Zeridium & Mirok - ONI Killer || FREE DOWNLOAD","Title_URL":"https://soundcloud.com/zeridium/zeridium-mirok-oni-killer-remix-2021-free-download","User":"\n                ZERIDIUM\n            ","User1":"","Time":"Posted 3 years ago\n3 years ago","Tag_URL":"https://soundcloud.com/tags/psytrance","Content":"Psytrance","Like":"1,699","scbuttonrepost":"656","scbuttoncopylink":"Copy Link","soundactions_purchaselink_URL":"https://gate.sc/?url=https%3A%2F%2Fhypeddit.com%2Ftrack%2Fdcpgav&token=f5f7a6-1-1736523135347","soundactions_purchaselink":"Free Download","scbuttonmore":"More","scministats":"24.3K","Comment_URL":"https://soundcloud.com/zeridium/zeridium-mirok-oni-killer-remix-2021-free-download/comments","Comment":"57"},{"Title":"Zeridium & Siloka - \"Your Kids Are Gonna Love it!\"","Title_URL":"https://soundcloud.com/zeridium/zeridium-siloka-your-kids-are-gonna-love-it-out-soon-on-sahman-records","User":"\n                ZERIDIUM\n            ","User1":"","Time":"Posted 3 years ago\n3 years ago","Tag_URL":"https://soundcloud.com/tags/psytrance","Content":"Psytrance","Like":"1,600","scbuttonrepost":"145","scbuttoncopylink":"Copy Link","soundactions_purchaselink_URL":"","soundactions_purchaselink":"","scbuttonmore":"More","scministats":"32.5K","Comment_URL":"https://soundcloud.com/zeridium/zeridium-siloka-your-kids-are-gonna-love-it-out-soon-on-sahman-records/comments","Comment":"118"},{"Title":"Zeridium - MoonRain || Out Now on Dacru Records","Title_URL":"https://soundcloud.com/zeridium/zeridium-moonrain-out-on-the-2610-on-dacru-records","User":"\n                ZERIDIUM\n            ","User1":"","Time":"Posted 4 years ago\n4 years ago","Tag_URL":"https://soundcloud.com/tags/psytrance","Content":"Psytrance","Like":"377","scbuttonrepost":"64","scbuttoncopylink":"Copy Link","soundactions_purchaselink_URL":"","soundactions_purchaselink":"","scbuttonmore":"More","scministats":"5,852","Comment_URL":"https://soundcloud.com/zeridium/zeridium-moonrain-out-on-the-2610-on-dacru-records/comments","Comment":"43"},{"Title":"Zeridium & Cambium - Rave Reactor","Title_URL":"https://soundcloud.com/zeridium/zeridium-cambium-rave-reactor-out-on-1409-on-sahman-records","User":"\n                ZERIDIUM\n            ","User1":"","Time":"Posted 4 years ago\n4 years ago","Tag_URL":"https://soundcloud.com/tags/psytrance","Content":"Psytrance","Like":"599","scbuttonrepost":"79","scbuttoncopylink":"Copy Link","soundactions_purchaselink_URL":"","soundactions_purchaselink":"","scbuttonmore":"More","scministats":"10.5K","Comment_URL":"https://soundcloud.com/zeridium/zeridium-cambium-rave-reactor-out-on-1409-on-sahman-records/comments","Comment":"64"},{"Title":"Zeridium & Oddwave - Kernschmelze  || Out on TesseracTstudio","Title_URL":"https://soundcloud.com/zeridium/zeridium-oddwave-kernschmelze-out-on-tesseractstudio-on-the-2506","User":"\n                ZERIDIUM\n            ","User1":"","Time":"Posted 4 years ago\n4 years ago","Tag_URL":"https://soundcloud.com/tags/industrial%20psytrance","Content":"Industrial Psytrance","Like":"294","scbuttonrepost":"45","scbuttoncopylink":"Copy Link","soundactions_purchaselink_URL":"","soundactions_purchaselink":"","scbuttonmore":"More","scministats":"5,334","Comment_URL":"https://soundcloud.com/zeridium/zeridium-oddwave-kernschmelze-out-on-tesseractstudio-on-the-2506/comments","Comment":"54"},{"Title":"Zeridium - Valhalla || FREE DOWNLOAD","Title_URL":"https://soundcloud.com/zeridium/zeridium-valhalla-free-download","User":"\n                ZERIDIUM\n            ","User1":"","Time":"Posted 4 years ago\n4 years ago","Tag_URL":"https://soundcloud.com/tags/psytrance","Content":"Psytrance","Like":"1,620","scbuttonrepost":"589","scbuttoncopylink":"Copy Link","soundactions_purchaselink_URL":"https://gate.sc/?url=https%3A%2F%2Fhypeddit.com%2Ftrack%2F52212m&token=a11acd-1-1736523135430","soundactions_purchaselink":"Free Download","scbuttonmore":"More","scministats":"22.1K","Comment_URL":"https://soundcloud.com/zeridium/zeridium-valhalla-free-download/comments","Comment":"108"},{"Title":"Zeridium & N-Kore - End Zone (Out on Nataraja's V.A album)","Title_URL":"https://soundcloud.com/zeridium/zeridium-n-kore-end-zone-out-soon-on-the-natarajas-va-album","User":"\n                ZERIDIUM\n            ","User1":"","Time":"Posted 4 years ago\n4 years ago","Tag_URL":"https://soundcloud.com/tags/psytrance","Content":"Psytrance","Like":"331","scbuttonrepost":"39","scbuttoncopylink":"Copy Link","soundactions_purchaselink_URL":"","soundactions_purchaselink":"","scbuttonmore":"More","scministats":"6,106","Comment_URL":"https://soundcloud.com/zeridium/zeridium-n-kore-end-zone-out-soon-on-the-natarajas-va-album/comments","Comment":"19"},{"Title":"Zeridium - Predators Experiment","Title_URL":"https://soundcloud.com/zeridium/zeridium-predators-experiments-out-now-on-sahman-records","User":"\n                Somos\n            ","User1":"","Time":"Posted 5 years ago\n5 years ago","Tag_URL":"https://soundcloud.com/tags/psytrance","Content":"Psytrance","Like":"552","scbuttonrepost":"91","scbuttoncopylink":"Copy Link","soundactions_purchaselink_URL":"","soundactions_purchaselink":"","scbuttonmore":"More","scministats":"9,505","Comment_URL":"https://soundcloud.com/zeridium/zeridium-predators-experiments-out-now-on-sahman-records/comments","Comment":"71"},{"Title":"Zeridium - WoodWoody","Title_URL":"https://soundcloud.com/zeridium/zeridium-woodwoody-out-on-now","User":"\n                ZERIDIUM\n            ","User1":"","Time":"Posted 5 years ago\n5 years ago","Tag_URL":"https://soundcloud.com/tags/psytrance","Content":"Psytrance","Like":"1,059","scbuttonrepost":"91","scbuttoncopylink":"Copy Link","soundactions_purchaselink_URL":"","soundactions_purchaselink":"","scbuttonmore":"More","scministats":"21K","Comment_URL":"https://soundcloud.com/zeridium/zeridium-woodwoody-out-on-now/comments","Comment":"90"},{"Title":"Zeridium Full Live Set @ Hadra Trance Festival 2019 (Main Stage)","Title_URL":"https://soundcloud.com/zeridium/zeridium-full-live-set-hadra-trance-festival-2019-main-stage","User":"\n                ZERIDIUM\n            ","User1":"","Time":"Posted 5 years ago\n5 years ago","Tag_URL":"https://soundcloud.com/tags/psytrance","Content":"Psytrance","Like":"1,144","scbuttonrepost":"168","scbuttoncopylink":"Copy Link","soundactions_purchaselink_URL":"https://gate.sc/?url=https%3A%2F%2Fwww.facebook.com%2F506118123057893%2Fvideos%2F630170364056633&token=6d54bc-1-1736523139365","soundactions_purchaselink":"Watch","scbuttonmore":"More","scministats":"20.3K","Comment_URL":"https://soundcloud.com/zeridium/zeridium-full-live-set-hadra-trance-festival-2019-main-stage/comments","Comment":"67"},{"Title":"Zeridium - Dodongo || Out on HADRA RECORDS","Title_URL":"https://soundcloud.com/zeridium/zeridium-dodongo-out-on-the-hadra-va-on-the-2908","User":"\n                Bionic (SA)\n            ","User1":"","Time":"Posted 5 years ago\n5 years ago","Tag_URL":"https://soundcloud.com/tags/psytrance","Content":"Psytrance","Like":"198","scbuttonrepost":"30","scbuttoncopylink":"Copy Link","soundactions_purchaselink_URL":"","soundactions_purchaselink":"","scbuttonmore":"More","scministats":"3,560","Comment_URL":"https://soundcloud.com/zeridium/zeridium-dodongo-out-on-the-hadra-va-on-the-2908/comments","Comment":"24"},{"Title":"Zeridium & Transient Disorder - Manipulation Of Time","Title_URL":"https://soundcloud.com/zeridium/zeridium-transient-disorder-manipulation-of-time","User":"\n                Micromoment, Spirit Architect\n            ","User1":"","Time":"Posted 5 years ago\n5 years ago","Tag_URL":"https://soundcloud.com/tags/psytrance","Content":"Psytrance","Like":"669","scbuttonrepost":"94","scbuttoncopylink":"Copy Link","soundactions_purchaselink_URL":"","soundactions_purchaselink":"","scbuttonmore":"More","scministats":"13.2K","Comment_URL":"https://soundcloud.com/zeridium/zeridium-transient-disorder-manipulation-of-time/comments","Comment":"45"},{"Title":"Zeridium - Dawn On Mars","Title_URL":"https://soundcloud.com/zeridium/zeridium-dawn-on-mars-out-now-on-sahman-records","User":"\n                ZERIDIUM\n            ","User1":"","Time":"Posted 6 years ago\n6 years ago","Tag_URL":"https://soundcloud.com/tags/psytrance","Content":"Psytrance","Like":"683","scbuttonrepost":"90","scbuttoncopylink":"Copy Link","soundactions_purchaselink_URL":"","soundactions_purchaselink":"","scbuttonmore":"More","scministats":"11.4K","Comment_URL":"https://soundcloud.com/zeridium/zeridium-dawn-on-mars-out-now-on-sahman-records/comments","Comment":"44"},{"Title":"Zeridium - Radioactive Ritual","Title_URL":"https://soundcloud.com/zeridium/zeridium-radioactive-ritual-out-now-on-sahman-records","User":"\n                Zeridium\n            ","User1":"","Time":"Posted 6 years ago\n6 years ago","Tag_URL":"https://soundcloud.com/tags/psytrance","Content":"Psytrance","Like":"900","scbuttonrepost":"138","scbuttoncopylink":"Copy Link","soundactions_purchaselink_URL":"","soundactions_purchaselink":"","scbuttonmore":"More","scministats":"15.3K","Comment_URL":"https://soundcloud.com/zeridium/zeridium-radioactive-ritual-out-now-on-sahman-records/comments","Comment":"71"},{"Title":"Zeridium - The Sacrifice","Title_URL":"https://soundcloud.com/zeridium/zeridium-the-sacrifice-out-now-on-sahman-records-va-album","User":"\n                ZERIDIUM\n            ","User1":"","Time":"Posted 6 years ago\n6 years ago","Tag_URL":"https://soundcloud.com/tags/psytrance","Content":"Psytrance","Like":"721","scbuttonrepost":"129","scbuttoncopylink":"Copy Link","soundactions_purchaselink_URL":"","soundactions_purchaselink":"","scbuttonmore":"More","scministats":"10.9K","Comment_URL":"https://soundcloud.com/zeridium/zeridium-the-sacrifice-out-now-on-sahman-records-va-album/comments","Comment":"98"},{"Title":"Zeridium VS Primary Lab || Out on Boom Shankar BMSS Records V.A","Title_URL":"https://soundcloud.com/zeridium/zeridium-vs-primary-lab-eivors-temple-out-soon-on-boom-shankar-bmss-records-va-album","User":"\n                ZERIDIUM\n            ","User1":"","Time":"Posted 6 years ago\n6 years ago","Tag_URL":"https://soundcloud.com/tags/psytrance","Content":"Psytrance","Like":"365","scbuttonrepost":"78","scbuttoncopylink":"Copy Link","soundactions_purchaselink_URL":"","soundactions_purchaselink":"","scbuttonmore":"More","scministats":"5,986","Comment_URL":"https://soundcloud.com/zeridium/zeridium-vs-primary-lab-eivors-temple-out-soon-on-boom-shankar-bmss-records-va-album/comments","Comment":"44"},{"Title":"Zeridium - System Reloaded || FREE DOWNLOAD","Title_URL":"https://soundcloud.com/zeridium/zeridium-system-reloaded-out-now-on-sahman-records","User":"\n                ZERIDIUM\n            ","User1":"","Time":"Posted 7 years ago\n7 years ago","Tag_URL":"https://soundcloud.com/tags/psytrance","Content":"Psytrance","Like":"1,034","scbuttonrepost":"187","scbuttoncopylink":"Copy Link","soundactions_purchaselink_URL":"","soundactions_purchaselink":"","scbuttonmore":"More","scministats":"17.5K","Comment_URL":"https://soundcloud.com/zeridium/zeridium-system-reloaded-out-now-on-sahman-records/comments","Comment":"107"},{"Title":"Zeridium - Magnetic Disturbance || FREE DOWNLOAD","Title_URL":"https://soundcloud.com/zeridium/electromagnetic-disturbance-preview-out-soon-on-sharp-noise-records","User":"\n                ZERIDIUM\n            ","User1":"","Time":"Posted 7 years ago\n7 years ago","Tag_URL":"https://soundcloud.com/tags/psytrance","Content":"Psytrance","Like":"581","scbuttonrepost":"99","scbuttoncopylink":"Copy Link","soundactions_purchaselink_URL":"","soundactions_purchaselink":"","scbuttonmore":"More","scministats":"9,628","Comment_URL":"https://soundcloud.com/zeridium/electromagnetic-disturbance-preview-out-soon-on-sharp-noise-records/comments","Comment":"63"},{"Title":"Zeridium - Intergalactic Agreement || FREE DOWNLOAD","Title_URL":"https://soundcloud.com/zeridium/intergalactic-agreement","User":"\n                ZERIDIUM\n            ","User1":"","Time":"Posted 7 years ago\n7 years ago","Tag_URL":"https://soundcloud.com/tags/psytrance","Content":"Psytrance","Like":"472","scbuttonrepost":"72","scbuttoncopylink":"Copy Link","soundactions_purchaselink_URL":"","soundactions_purchaselink":"","scbuttonmore":"More","scministats":"9,322","Comment_URL":"https://soundcloud.com/zeridium/intergalactic-agreement/comments","Comment":"39"},{"Title":"Zeridium - ॐ Indian Storm || FREE DOWNLOAD","Title_URL":"https://soundcloud.com/zeridium/indian-storm","User":"\n                ZERIDIUM\n            ","User1":"","Time":"Posted 9 years ago\n9 years ago","Tag_URL":"https://soundcloud.com/tags/spiritual%20progressive","Content":"Spiritual Progressive","Like":"1,243","scbuttonrepost":"57","scbuttoncopylink":"Copy Link","soundactions_purchaselink_URL":"","soundactions_purchaselink":"","scbuttonmore":"More","scministats":"28.5K","Comment_URL":"https://soundcloud.com/zeridium/indian-storm/comments","Comment":"23"}]